AliHenidy/__init__.py
AliHenidy/calculator.py
AliHenidy-0.0.1.dist-info/LICENSE
AliHenidy-0.0.1.dist-info/METADATA
AliHenidy-0.0.1.dist-info/WHEEL
AliHenidy-0.0.1.dist-info/top_level.txt
AliHenidy-0.0.1.dist-info/RECORD
