Metadata-Version: 2.1
Name: AliHenidy
Version: 0.0.1
Summary: A small example package
Author: Brad
Author-email: devopswithbrad@gmail.com
Classifier: Programming Language :: Python :: 3
Classifier: License :: OSI Approved :: MIT License
Classifier: Operating System :: OS Independent
Requires-Python: >=3.6
License-File: LICENSE
